{
  "tax_id": "0103520004801",
  "ชื่อ": "ห้างหุ้นส่วนจำกัด แอ๊ดวานซ์ เอ็นจิเนียริ่ง แอนด์ ดีไซน์",
  "เลขทะเบียน": "0103520004801",
  "สถานะ": "ยังดำเนินกิจการอยู่",
  "วันที่จดทะเบียน": "16 มี.ค. 2520",
  "ทุนจดทะเบียน": "2,000,000.00 บาท",
  "กลุ่มธุรกิจ": "ขายส่ง",
  "ขนาดธุรกิจ": "S",
  "ที่ตั้งสำนักงานใหญ่": "640/2-3 ซอยแก้วฟ้า ถนนสี่พระยา  แขวงมหาพฤฒาราม เขตบางรัก กรุงเทพมหานคร",
  "กรรมการ": "-",
  "TSIC ตอนจดทะเบียน": "46421 การขายส่งเครื่องใช้ไฟฟ้าและอิเล็กทรอนิกส์ชนิดใช้ในครัวเรือน",
  "วัตถุประสงค์ตอนจดทะเบียน": "ขายเครื่องปรับอากาศ รับจ้างซ่อมแซม",
  "TSIC ล่าสุด": "46421 การขายส่งเครื่องใช้ไฟฟ้าและอิเล็กทรอนิกส์ชนิดใช้ในครัวเรือน",
  "วัตถุประสงค์ล่าสุด": "จำหน่ายเครื่องปรับอากาศ",
  "fetched_at_utc": "2025-08-15T09:13:13Z"
}