{
  "tax_id": "0105558190042",
  "ชื่อ": "บริษัท เดอะ รัช ไนน์ทีน โฮเต็ล จำกัด",
  "เลขทะเบียน": "0105558190042",
  "สถานะ": "ยังดำเนินกิจการอยู่",
  "วันที่จดทะเบียน": "03 ธ.ค. 2558",
  "ทุนจดทะเบียน": "5,000,000.00 บาท",
  "กลุ่มธุรกิจ": "บริการ",
  "ขนาดธุรกิจ": "S",
  "ที่ตั้งสำนักงานใหญ่": "65  ซอยนาทอง ถนนรัชดาภิเษก แขวงดินแดง เขตดินแดง กรุงเทพมหานคร",
  "กรรมการ": "นายเสมือน  พยอม",
  "TSIC ตอนจดทะเบียน": "55101 โรงแรม รีสอร์ทและห้องชุด",
  "วัตถุประสงค์ตอนจดทะเบียน": "ประกอบกิจการโรงแรม ห้องพักอาศัย คอฟฟี่ช๊อป และอาบ อบ นวด เพื่อสุขภาพ สปา",
  "TSIC ล่าสุด": "96305 กิจกรรมการบริการอาบอบนวดและการบริการอื่นๆที่คล้ายกัน",
  "วัตถุประสงค์ล่าสุด": "สถานบริการ อาบ อบ นวด โรงแรม ภัตตาคาร บาร์ ไนท์คลับ",
  "fetched_at_utc": "2025-08-12T13:59:12Z"
}