{
  "tax_id": "0105560185433",
  "ชื่อ": "บริษัท ท็อป เซอร์วิส ออโต้ เทคนิค จำกัด",
  "เลขทะเบียน": "0105560185433",
  "สถานะ": "ยังดำเนินกิจการอยู่",
  "วันที่จดทะเบียน": "03 พ.ย. 2560",
  "ทุนจดทะเบียน": "5,000,000.00 บาท",
  "กลุ่มธุรกิจ": "ขายส่ง",
  "ขนาดธุรกิจ": "S",
  "ที่ตั้งสำนักงานใหญ่": "9  ซอยนิมิตใหม่ 61 แขวงสามวาตะวันออก เขตคลองสามวา กรุงเทพมหานคร",
  "กรรมการ": "นายศุภเชษฐ  เหมือนตรี, นายนาวี  วีระนนท์, นายอัฑฒกร  อร่ามศรี, นางสาวนลินฉัตร์  ศรุตาวรธนาศิริ",
  "TSIC ตอนจดทะเบียน": "45201 การบำรุงรักษาและการซ่อมระบบเครื่องยนต์และชิ้นส่วนยานยนต์",
  "วัตถุประสงค์ตอนจดทะเบียน": "ประกอบกิจการบริการ ซ่อมแซม บำรุงรักษา ตรวจสภาพ ยานพาหนะ รถยนต์และรถซุปเปอร์คาร์",
  "TSIC ล่าสุด": "45201 การบำรุงรักษาและการซ่อมระบบเครื่องยนต์และชิ้นส่วนยานยนต์",
  "วัตถุประสงค์ล่าสุด": "ให้บริการซ่อมแซมบำรุงรักษา ยานพาหนะ",
  "fetched_at_utc": "2025-08-12T09:29:37Z"
}