{
  "tax_id": "0105558193343",
  "ชื่อ": "บริษัท โคซี่บางกอก จำกัด",
  "เลขทะเบียน": "0105558193343",
  "สถานะ": "ยังดำเนินกิจการอยู่",
  "วันที่จดทะเบียน": "14 ธ.ค. 2558",
  "ทุนจดทะเบียน": "50,000,000.00 บาท",
  "กลุ่มธุรกิจ": "บริการ",
  "ขนาดธุรกิจ": "S",
  "ที่ตั้งสำนักงานใหญ่": "10  ซอยรัชฏภัณฑ์ แขวงมักกะสัน เขตราชเทวี กรุงเทพมหานคร",
  "กรรมการ": "นายศุภวุฒิ  ธรรมสาร, นางสาวขวัญยิหวา  วามนตรี",
  "TSIC ตอนจดทะเบียน": "55101 โรงแรม รีสอร์ทและห้องชุด",
  "วัตถุประสงค์ตอนจดทะเบียน": "โรงแรม รีสอร์ท ห้องชุด",
  "TSIC ล่าสุด": "55101 โรงแรม รีสอร์ทและห้องชุด",
  "วัตถุประสงค์ล่าสุด": "โรงแรม รีสอร์ทและห้องชุด",
  "fetched_at_utc": "2025-08-12T13:58:34Z"
}