{
  "tax_id": "0105553092956",
  "ชื่อ": "บริษัท โรส อาร์ทิสท์ เมเนจเม้นท์  จำกัด",
  "เลขทะเบียน": "0105553092956",
  "สถานะ": "ยังดำเนินกิจการอยู่",
  "วันที่จดทะเบียน": "02 ส.ค. 2553",
  "ทุนจดทะเบียน": "20,000,000.00 บาท",
  "กลุ่มธุรกิจ": "บริการ",
  "ขนาดธุรกิจ": "S",
  "ที่ตั้งสำนักงานใหญ่": "23/85 ซอยลาดพร้าว 23 ถนนลาดพร้าว  แขวงจันทรเกษม เขตจตุจักร กรุงเทพมหานคร",
  "กรรมการ": "นางอรพรรณ มนต์พิชิต  บวรวัฒนะ, นายวรวิทย์  บวรวัฒนะ, นายณัฐพล  บวรวัฒนะ",
  "TSIC ตอนจดทะเบียน": "56101 การบริการด้านอาหารในภัตตาคาร/ร้านอาหาร",
  "วัตถุประสงค์ตอนจดทะเบียน": "ประกอบกิจการจำหน่ายอาหาร อาหารสำเร็จรูปพร้อมรับประทานและเครื่องดื่มทุกชนิด",
  "TSIC ล่าสุด": "73102 กิจกรรมของตัวแทนขายสื่อโฆษณา",
  "วัตถุประสงค์ล่าสุด": "ตัวแทนซื้อและขายรายการโทรทัศน์และภาพยนต์",
  "fetched_at_utc": "2025-08-12T21:56:22Z"
}