{
  "tax_id": "0105561193529",
  "ชื่อ": "บริษัท ซีที พร็อพเพอร์ตี้ แมเนจเม้นท์ จำกัด",
  "เลขทะเบียน": "0105561193529",
  "สถานะ": "ยังดำเนินกิจการอยู่",
  "วันที่จดทะเบียน": "12 พ.ย. 2561",
  "ทุนจดทะเบียน": "5,000,000.00 บาท",
  "กลุ่มธุรกิจ": "บริการ",
  "ขนาดธุรกิจ": "S",
  "ที่ตั้งสำนักงานใหญ่": "144/25  ถนนสีลม แขวงสุริยวงศ์ เขตบางรัก กรุงเทพมหานคร",
  "กรรมการ": "นางสาวสุกันยา  สิริฤทัย, นายสรวิศ  จะงือ, นายสรสิช  จะงือ",
  "TSIC ตอนจดทะเบียน": "68102 การซื้อและการขายอสังหาริมทรัพย์ที่เป็นของตนเองที่ไม่ใช่ เพื่อเป็นที่พักอาศัย",
  "วัตถุประสงค์ตอนจดทะเบียน": "ซื้อ ขาย เช่า อสังหาริมทรัพย์",
  "TSIC ล่าสุด": "68201 กิจกรรมของตัวแทนและนายหน้าอสังหาริมทรัพย์โดยได้รับ ค่าตอบแทนหรือตามสัญญาจ้าง",
  "วัตถุประสงค์ล่าสุด": "อสังหาริมทรัพย์",
  "fetched_at_utc": "2025-08-12T07:00:06Z"
}