{
  "tax_id": "0105562038608",
  "ชื่อ": "บริษัท วายเค มอเตอร์สปอร์ต จำกัด",
  "เลขทะเบียน": "0105562038608",
  "สถานะ": "ยังดำเนินกิจการอยู่",
  "วันที่จดทะเบียน": "26 ก.พ. 2562",
  "ทุนจดทะเบียน": "1,000,000.00 บาท",
  "กลุ่มธุรกิจ": "ขายส่ง",
  "ขนาดธุรกิจ": "S",
  "ที่ตั้งสำนักงานใหญ่": "103/6  ถนนสะแกงาม แขวงแสมดำ เขตบางขุนเทียน กรุงเทพมหานคร",
  "กรรมการ": "นางสาวณัฐนิช  ลีวัฒนาวรากุล, นายภาสฤทธิ์  พรหมสมบัติ",
  "TSIC ตอนจดทะเบียน": "45301 การขายส่งชิ้นส่วนและอุปกรณ์เสริมใหม่ของยานยนต์",
  "วัตถุประสงค์ตอนจดทะเบียน": "นำเข้า ขายส่งชิ้นส่วน อุปกรณ์ และอะไหล่รถยนต์",
  "TSIC ล่าสุด": "45301 การขายส่งชิ้นส่วนและอุปกรณ์เสริมใหม่ของยานยนต์",
  "วัตถุประสงค์ล่าสุด": "ขายส่งชิ้นส่วนอุปกรณ์และอะไหล่รถยนต์",
  "fetched_at_utc": "2025-08-12T06:24:44Z"
}