{
  "tax_id": "0105562005971",
  "ชื่อ": "บริษัท ชีวะธนรักษ์ จำกัด",
  "เลขทะเบียน": "0105562005971",
  "สถานะ": "ยังดำเนินกิจการอยู่",
  "วันที่จดทะเบียน": "11 ม.ค. 2562",
  "ทุนจดทะเบียน": "1,500,000.00 บาท",
  "กลุ่มธุรกิจ": "บริการ",
  "ขนาดธุรกิจ": "S",
  "ที่ตั้งสำนักงานใหญ่": "71  หมู่ที่ 8 ต.บางจาก อ.พระประแดง จ.สมุทรปราการ",
  "กรรมการ": "นายธานัท  ชีวะธนรักษ์, นายพสิษฐ์  ชีวะธนรักษ์, นายภิญญู  ชีวะธนรักษ์, นางชนกฤชา  รัตนวงศ์สวัสดิ์, นางสาวต้องตา  อาชาเทวัญ",
  "TSIC ตอนจดทะเบียน": "68102 การซื้อและการขายอสังหาริมทรัพย์ที่เป็นของตนเองที่ไม่ใช่ เพื่อเป็นที่พักอาศัย",
  "วัตถุประสงค์ตอนจดทะเบียน": "ประกอบกิจการซื้อมาขายไปอสังหาริมทรัพย์ สร้างอาคารเพื่อขาย",
  "TSIC ล่าสุด": "68102 การซื้อและการขายอสังหาริมทรัพย์ที่เป็นของตนเองที่ไม่ใช่ เพื่อเป็นที่พักอาศัย",
  "วัตถุประสงค์ล่าสุด": "ให้บริการเช่าพื้นที่ จำหน่ายแฟชั่นและเครื่องเขียน อุปกรณ์ ตกแต่งและของใช้ภายในบ้าน",
  "fetched_at_utc": "2025-08-12T06:54:04Z"
}