{
  "tax_id": "0105554125793",
  "ชื่อ": "บริษัท วี.เอ็ม.เอส. คาร์ เซลล์ จำกัด",
  "เลขทะเบียน": "0105554125793",
  "สถานะ": "ยังดำเนินกิจการอยู่",
  "วันที่จดทะเบียน": "20 ก.ย. 2554",
  "ทุนจดทะเบียน": "10,000,000.00 บาท",
  "กลุ่มธุรกิจ": "ขายส่ง",
  "ขนาดธุรกิจ": "S",
  "ที่ตั้งสำนักงานใหญ่": "70 ถนนนวมินทร์  แขวงคลองกุ่ม เขตบึงกุ่ม กรุงเทพมหานคร",
  "กรรมการ": "นายธงชัย  จิรอลงกรณ์, นายวิเลิศ  ด่านขุนทด, นางสาวนงค์นุช  วัฒนสุนทรกุล, นายนคร  อรุณมีศรี, นายอิทธิโชติ  สิราภาสกุล, นายพุฒิพันธุ์  ธรรมวิชัย, นางสาวสิทธินรี  ลาภธนานุกูล",
  "TSIC ตอนจดทะเบียน": "45101 การขายยานยนต์ใหม่ชนิดรถยนต์นั่งส่วนบุคคลรถกระบะรถตู้ และรถขนาดเล็กที่คล้ายกัน",
  "วัตถุประสงค์ตอนจดทะเบียน": "ประกอบกิจการซื้อ ขาย แลกเปลี่ยนรถยนต์ ตลอดจนยานพาหนะทุกประเภท",
  "TSIC ล่าสุด": "45101 การขายยานยนต์ใหม่ชนิดรถยนต์นั่งส่วนบุคคลรถกระบะรถตู้ และรถขนาดเล็กที่คล้ายกัน",
  "วัตถุประสงค์ล่าสุด": "การขายยานยนต์ใหม่ชนิดรถยนต์นั่งส่วนบุคคล",
  "fetched_at_utc": "2025-08-12T20:31:55Z"
}