{
  "tax_id": "0105551091057",
  "ชื่อ": "บริษัท สยาม รชตะ จำกัด",
  "เลขทะเบียน": "0105551091057",
  "สถานะ": "ยังดำเนินกิจการอยู่",
  "วันที่จดทะเบียน": "14 ส.ค. 2551",
  "ทุนจดทะเบียน": "3,000,000.00 บาท",
  "กลุ่มธุรกิจ": "บริการ",
  "ขนาดธุรกิจ": "S",
  "ที่ตั้งสำนักงานใหญ่": "731  อาคารพีเอ็มทาวเวอร์ ชั้น 15 ถนนอโศก-ดินแดง แขวงดินแดง เขตดินแดง กรุงเทพมหานคร",
  "กรรมการ": "นายพิสิษฐ์  รุ่งไพบูลย์กุล",
  "TSIC ตอนจดทะเบียน": "71101 กิจกรรมงานสถาปัตยกรรมและการให้คำปรึกษาที่เกี่ยวข้อง",
  "วัตถุประสงค์ตอนจดทะเบียน": "ประกอบกิจการให้บริการ ออกแบบงานก่อสร้างทุกชนิด ออกแบบสถาปัตยกรรมและวิศวกรรมเกี่ยวกับก่อสร้าง",
  "TSIC ล่าสุด": "43210 การติดตั้งไฟฟ้า",
  "วัตถุประสงค์ล่าสุด": "ให้บริการ ออกแบบงานก่อสร้างทุกชนิด ออกแบบสถาปัตยกรรม และวิศวกรรมเกี่ยวกับการก่อสร้างทุกชนิด",
  "fetched_at_utc": "2025-08-13T00:12:25Z"
}