{
  "tax_id": "0105561165860",
  "ชื่อ": "บริษัท เวลา นาใต้ เรสซิเดนเซส (วิลล่า) จำกัด",
  "เลขทะเบียน": "0105561165860",
  "สถานะ": "ยังดำเนินกิจการอยู่",
  "วันที่จดทะเบียน": "25 ก.ย. 2561",
  "ทุนจดทะเบียน": "20,000,000.00 บาท",
  "กลุ่มธุรกิจ": "บริการ",
  "ขนาดธุรกิจ": "S",
  "ที่ตั้งสำนักงานใหญ่": "208 ชั้น 3 ห้อง 301  ถนนวิทยุ แขวงลุมพินี เขตปทุมวัน กรุงเทพมหานคร",
  "กรรมการ": "นางประภาวดี  โสภณพนิช, นายโชน  โสภณพนิช",
  "TSIC ตอนจดทะเบียน": "68102 การซื้อและการขายอสังหาริมทรัพย์ที่เป็นของตนเองที่ไม่ใช่ เพื่อเป็นที่พักอาศัย",
  "วัตถุประสงค์ตอนจดทะเบียน": "ประกอบกิจการเกี่ยวกับการพัฒนาและการลงทุนในที่ดินและอสังหาริมทรัพย์ทุกประเภทเพื่อการพาณิชย์",
  "TSIC ล่าสุด": "68102 การซื้อและการขายอสังหาริมทรัพย์ที่เป็นของตนเองที่ไม่ใช่ เพื่อเป็นที่พักอาศัย",
  "วัตถุประสงค์ล่าสุด": "การซื้อและการขายอสังหาริมทรัพย์ที่เป็นของตนเองที่ไม่ใช่เพื่อเป็นที่พักอาศัย",
  "fetched_at_utc": "2025-08-12T07:20:33Z"
}