{
  "tax_id": "0105561002707",
  "ชื่อ": "บริษัท สยาม ชาร์มมิ่ง จำกัด",
  "เลขทะเบียน": "0105561002707",
  "สถานะ": "ยังดำเนินกิจการอยู่",
  "วันที่จดทะเบียน": "08 ม.ค. 2561",
  "ทุนจดทะเบียน": "1,000,000.00 บาท",
  "กลุ่มธุรกิจ": "บริการ",
  "ขนาดธุรกิจ": "S",
  "ที่ตั้งสำนักงานใหญ่": "1410/8  ถนนประชาชื่น แขวงวงศ์สว่าง เขตบางซื่อ กรุงเทพมหานคร",
  "กรรมการ": "นางสาวนิยุตา  แซ่อุ่ย",
  "TSIC ตอนจดทะเบียน": "56101 การบริการด้านอาหารในภัตตาคาร/ร้านอาหาร",
  "วัตถุประสงค์ตอนจดทะเบียน": "ประกอบกิจการจำหน่ายอาหารและเครื่องดื่ม (ร้านอาหาร)",
  "TSIC ล่าสุด": "56101 การบริการด้านอาหารในภัตตาคาร/ร้านอาหาร",
  "วัตถุประสงค์ล่าสุด": "การบริการด้านอาหารในภัตตาคาร/ร้านอาหาร",
  "fetched_at_utc": "2025-08-12T09:00:45Z"
}