{
  "tax_id": "0105561047549",
  "ชื่อ": "บริษัท ออเร้นจ์ ริเวอร์ เจมส์ จำกัด",
  "เลขทะเบียน": "0105561047549",
  "สถานะ": "ยังดำเนินกิจการอยู่",
  "วันที่จดทะเบียน": "14 มี.ค. 2561",
  "ทุนจดทะเบียน": "5,000,000.00 บาท",
  "กลุ่มธุรกิจ": "ขายปลีก",
  "ขนาดธุรกิจ": "S",
  "ที่ตั้งสำนักงานใหญ่": "7/5  ซอยสุขาภิบาล 5 ซอย 5 แยก 1 แขวงท่าแร้ง เขตบางเขน กรุงเทพมหานคร",
  "กรรมการ": "นางสาวคัณธรส  หาญไชยพิบูลย์กุล",
  "TSIC ตอนจดทะเบียน": "82301 การจัดการประชุม",
  "วัตถุประสงค์ตอนจดทะเบียน": "ให้การฝึกอบรม กิจกรรมสันทนาการ และสัมมนาความรู้ ด้านวิชาการทุกสาขาวิชา ความรู้ด้านคอมพิวเตอร์ ด้านการสื่อสารเทคโนโลยีสมัยใหม่ เป็นนายหน้า ตัวแทน จัดอบรม สัมมนาทั้งในและต่างประเทศ",
  "TSIC ล่าสุด": "47732 ร้านขายปลีกเครื่องประดับ",
  "วัตถุประสงค์ล่าสุด": "จำหน่ายปลีกจิวเวลรี่ เพชร ทอง พลอยและอัญมณี",
  "fetched_at_utc": "2025-08-12T08:26:04Z"
}