{
  "tax_id": "0105553136724",
  "ชื่อ": "บริษัท วี พี คิว เพลส จำกัด",
  "เลขทะเบียน": "0105553136724",
  "สถานะ": "ยังดำเนินกิจการอยู่",
  "วันที่จดทะเบียน": "04 พ.ย. 2553",
  "ทุนจดทะเบียน": "4,000,000.00 บาท",
  "กลุ่มธุรกิจ": "บริการ",
  "ขนาดธุรกิจ": "S",
  "ที่ตั้งสำนักงานใหญ่": "211/1 ถนนพุทธมณฑลสาย 1  แขวงบางด้วน เขตภาษีเจริญ กรุงเทพมหานคร",
  "กรรมการ": "นายวีรพงศ์  เกษดำรงพาณิชย์, นายณรงค์ชัย  เกษดำรงพาณิชย์",
  "TSIC ตอนจดทะเบียน": "68103 การเช่าและการดำเนินการเกี่ยวกับอสังหาริมทรัพย์ที่เป็น ของตนเองหรือเช่าจากผู้อื่นเพื่อเป็นที่พักอาศัย",
  "วัตถุประสงค์ตอนจดทะเบียน": "ประกอบกิจการให้บริการเช่าอพาร์เม้นท์ หอพัก โฮมออฟฟิศ",
  "TSIC ล่าสุด": "68103 การเช่าและการดำเนินการเกี่ยวกับอสังหาริมทรัพย์ที่เป็น ของตนเองหรือเช่าจากผู้อื่นเพื่อเป็นที่พักอาศัย",
  "วัตถุประสงค์ล่าสุด": "ประกอบกิจการให้บริการเช่าอพาร์ทเม้นท์ หอพัก โฮมออฟฟิศ",
  "fetched_at_utc": "2025-08-12T21:18:55Z"
}