{
  "tax_id": "0105553093154",
  "ชื่อ": "บริษัท เอสเอสดี สตูดิโอ จำกัด",
  "เลขทะเบียน": "0105553093154",
  "สถานะ": "ยังดำเนินกิจการอยู่",
  "วันที่จดทะเบียน": "03 ส.ค. 2553",
  "ทุนจดทะเบียน": "2,000,000.00 บาท",
  "กลุ่มธุรกิจ": "ขายปลีก",
  "ขนาดธุรกิจ": "S",
  "ที่ตั้งสำนักงานใหญ่": "2/2  อาคารภักดี ชั้น 1 ถนนวิทยุ แขวงลุมพินี เขตปทุมวัน กรุงเทพมหานคร",
  "กรรมการ": "นายพลวุฒิ  โพธิรัตนังกูร",
  "TSIC ตอนจดทะเบียน": "56101 การบริการด้านอาหารในภัตตาคาร/ร้านอาหาร",
  "วัตถุประสงค์ตอนจดทะเบียน": "ประกอบกิจการร้านอาหาร",
  "TSIC ล่าสุด": "47591 ร้านขายปลีกเฟอร์นิเจอร์ชนิดใช้ในครัวเรือน",
  "วัตถุประสงค์ล่าสุด": "ขายเฟอร์นิเจอร์",
  "fetched_at_utc": "2025-08-12T21:56:10Z"
}