{
  "tax_id": "0105561130276",
  "ชื่อ": "บริษัท พีเคพี อินเตอร์ เทรดดิ้ง (ประเทศไทย) จำกัด",
  "เลขทะเบียน": "0105561130276",
  "สถานะ": "ยังดำเนินกิจการอยู่",
  "วันที่จดทะเบียน": "31 ก.ค. 2561",
  "ทุนจดทะเบียน": "1,000,000.00 บาท",
  "กลุ่มธุรกิจ": "ขายส่ง",
  "ขนาดธุรกิจ": "S",
  "ที่ตั้งสำนักงานใหญ่": "22/126  อาคารศูนย์รวมรถยนต์ ออโต้ โซน2 บล็อกบี1 ถนนคลองลำเจียก แขวงนวมินทร์ เขตบึงกุ่ม กรุงเทพมหานคร",
  "กรรมการ": "นางสาวริญญาภัทร์  สถิตย์พรกิตติ, นายพลัฏฐ์  วิทยานิธิธรณ์",
  "TSIC ตอนจดทะเบียน": "45101 การขายยานยนต์ใหม่ชนิดรถยนต์นั่งส่วนบุคคลรถกระบะรถตู้ และรถขนาดเล็กที่คล้ายกัน",
  "วัตถุประสงค์ตอนจดทะเบียน": "ประกอบกิจการ จำหน่าย รับจำนำ รถยนต์ทุกชนิด รถยนต์ใช้แล้ว รวมทั้งอะไหล่และอุปกรณ์รถยนต์ทุกชนิด",
  "TSIC ล่าสุด": "45101 การขายยานยนต์ใหม่ชนิดรถยนต์นั่งส่วนบุคคลรถกระบะรถตู้ และรถขนาดเล็กที่คล้ายกัน",
  "วัตถุประสงค์ล่าสุด": "สินค้า",
  "fetched_at_utc": "2025-08-12T07:38:55Z"
}