{
  "tax_id": "0105551048453",
  "ชื่อ": "บริษัท ฟลอรอล ไชร์ จำกัด",
  "เลขทะเบียน": "0105551048453",
  "สถานะ": "ยังดำเนินกิจการอยู่",
  "วันที่จดทะเบียน": "02 พ.ค. 2551",
  "ทุนจดทะเบียน": "1,000,000.00 บาท",
  "กลุ่มธุรกิจ": "บริการ",
  "ขนาดธุรกิจ": "S",
  "ที่ตั้งสำนักงานใหญ่": "56 ซอยลาดกระบัง 42  แขวงลาดกระบัง เขตลาดกระบัง กรุงเทพมหานคร",
  "กรรมการ": "นายวศิน  วงศ์พรภักดี, นายฐกณ  วงศ์พรภักดี",
  "TSIC ตอนจดทะเบียน": "68103 การเช่าและการดำเนินการเกี่ยวกับอสังหาริมทรัพย์ที่เป็น ของตนเองหรือเช่าจากผู้อื่นเพื่อเป็นที่พักอาศัย",
  "วัตถุประสงค์ตอนจดทะเบียน": "ประกอบกิจการให้เช่าอาคารที่พักอาศัย อพาร์ทเม้นท์",
  "TSIC ล่าสุด": "68103 การเช่าและการดำเนินการเกี่ยวกับอสังหาริมทรัพย์ที่เป็น ของตนเองหรือเช่าจากผู้อื่นเพื่อเป็นที่พักอาศัย",
  "วัตถุประสงค์ล่าสุด": "ให้เช่าที่พักอาศัย อพาร์ทเม้นท์เซอร์วิส",
  "fetched_at_utc": "2025-08-13T01:17:27Z"
}