{
  "tax_id": "0105545060731",
  "ชื่อ": "บริษัท เลเว็นโต้  จำกัด",
  "เลขทะเบียน": "0105545060731",
  "สถานะ": "ยังดำเนินกิจการอยู่",
  "วันที่จดทะเบียน": "13 มิ.ย. 2545",
  "ทุนจดทะเบียน": "200,000,000.00 บาท",
  "กลุ่มธุรกิจ": "บริการ",
  "ขนาดธุรกิจ": "S",
  "ที่ตั้งสำนักงานใหญ่": "70/39  ซอยบุญอยู่ ถนนดินแดง แขวงสามเสนใน เขตพญาไท กรุงเทพมหานคร",
  "กรรมการ": "นางสาวสิรินาฏ  สืบสวน, นายวิโรจน์  คงทวี",
  "TSIC ตอนจดทะเบียน": "46106 การขายส่งเชื้อเพลิงสินแร่โลหะโดยได้รับค่าตอบแทนหรือตามสัญญาจ้าง",
  "วัตถุประสงค์ตอนจดทะเบียน": "ประกอบกิจการนำเข้า ส่งออก ซื้อ ขาย จัดหา จัดจำหน่าย เป็นตัวแทน นายหน้า หรือค้าส่ง ค้าปลีก น้ำมันเชื้อเพลิงทุกชนิด ทั้งในประเทศและต่างประเทศ รวมถึงน้ำมันดิบ น้ำมันสำเร็จรูป น้ำมันดีเซล น้ำมันเบนซิน น้ำมันเตา น้ำมันหล่อลื่น น้ำมันเครื่อง และผลิตภัณฑ์ปิโตรเลียมอื่น ๆ รวมทั้งผลิตภัณฑ์ที่ได้ จากน้ำมันหรือก๊าซธรรมชาติ",
  "TSIC ล่าสุด": "73101 กิจกรรมของบริษัทโฆษณา",
  "วัตถุประสงค์ล่าสุด": "ประกอบกิจการให้บริการจัดสถานที่",
  "fetched_at_utc": "2025-08-13T10:04:17Z"
}