{
  "tax_id": "0105557060498",
  "ชื่อ": "บริษัท ภีรณิชา จำกัด",
  "เลขทะเบียน": "0105557060498",
  "สถานะ": "ยังดำเนินกิจการอยู่",
  "วันที่จดทะเบียน": "29 เม.ย. 2557",
  "ทุนจดทะเบียน": "2,000,000.00 บาท",
  "กลุ่มธุรกิจ": "บริการ",
  "ขนาดธุรกิจ": "S",
  "ที่ตั้งสำนักงานใหญ่": "1031 อาคารศูนย์การค้า เซ็นทรัลแอมบาสซี ห้องเลขที่ แอล 4-03 ถนนเพลินจิต  แขวงลุมพินี เขตปทุมวัน กรุงเทพมหานคร",
  "กรรมการ": "นางอนันยา  เศรษฐนันท์, นางจินตนา  เตชาพลาเลิศ",
  "TSIC ตอนจดทะเบียน": "96104 กิจกรรมการดูแลความงามแต่งเล็บมือและเล็บเท้า",
  "วัตถุประสงค์ตอนจดทะเบียน": "ประกอบกิจการ เสริมความงาม",
  "TSIC ล่าสุด": "96104 กิจกรรมการดูแลความงามแต่งเล็บมือและเล็บเท้า",
  "วัตถุประสงค์ล่าสุด": "ประกอบกิจการ เสริมความงาม",
  "fetched_at_utc": "2025-08-12T16:29:26Z"
}