{
  "tax_id": "0105549114584",
  "ชื่อ": "บริษัท อีโค่อิสซึ่ม  จำกัด",
  "เลขทะเบียน": "0105549114584",
  "สถานะ": "ยังดำเนินกิจการอยู่",
  "วันที่จดทะเบียน": "25 ก.ย. 2549",
  "ทุนจดทะเบียน": "60,000,000.00 บาท",
  "กลุ่มธุรกิจ": "บริการ",
  "ขนาดธุรกิจ": "S",
  "ที่ตั้งสำนักงานใหญ่": "304  ถนนลำพูน ต.วัดเกต อ.เมืองเชียงใหม่ จ.เชียงใหม่",
  "กรรมการ": "นายเจริญ  ชุมภูคำ, นายกิติ  สุภัคคุณธรรม, นายหลิว เจ๋อ  หยาง",
  "TSIC ตอนจดทะเบียน": "70209 กิจกรรมให้คำปรึกษาด้านการบริหารจัดการอื่นๆซึ่งมิได้จัด ประเภทไว้ในที่อื่น",
  "วัตถุประสงค์ตอนจดทะเบียน": "รับจ้างผลิตหนังสือ สื่อ สิ่งพิมพ์ ทุกประเภท",
  "TSIC ล่าสุด": "55101 โรงแรม รีสอร์ทและห้องชุด",
  "วัตถุประสงค์ล่าสุด": "โรงแรม รีสอร์ทและห้องชุด",
  "fetched_at_utc": "2025-08-13T04:55:42Z"
}