{
  "tax_id": "0105552090607",
  "ชื่อ": "บริษัท วี.เอ็ม. คาเมร่ากรุ๊ป จำกัด",
  "เลขทะเบียน": "0105552090607",
  "สถานะ": "ยังดำเนินกิจการอยู่",
  "วันที่จดทะเบียน": "01 ก.ย. 2552",
  "ทุนจดทะเบียน": "1,000,000.00 บาท",
  "กลุ่มธุรกิจ": "ขายส่ง",
  "ขนาดธุรกิจ": "S",
  "ที่ตั้งสำนักงานใหญ่": "5 อาคารฟอร์จูนทาวน์ ชั้น 4 ห้อง 24-25 โซนพลาซ่า ถนนรัชดาภิเษก  แขวงดินแดง เขตดินแดง กรุงเทพมหานคร",
  "กรรมการ": "นางอชิดา  ชะบางาม",
  "TSIC ตอนจดทะเบียน": "47731 ร้านขายปลีกนาฬิกาแว่นตาและอุปกรณ์ถ่ายภาพ",
  "วัตถุประสงค์ตอนจดทะเบียน": "ประกอบกิจการรับซื้อ จำหน่าย นำเข้า แลกเปลี่ยน ฝากขาย ให้เช่า ให้ซื้อกล้องและอุปกรณ์สื่อบันทึกทุกชนิด",
  "TSIC ล่าสุด": "46491 การขายส่งอุปกรณ์ถ่ายภาพและทัศนศาสตร์",
  "วัตถุประสงค์ล่าสุด": "บริการซ่อมกล้องถ่ายรูปจำหน่ายอุปกรณ์เกี่ยวกับกล้องถ่ายรูป",
  "fetched_at_utc": "2025-08-12T22:45:40Z"
}