{
  "tax_id": "0105556086736",
  "ชื่อ": "บริษัท หัวซิน คังหมิ๋น การจัดการสุขภาพ (ประเทศไทย) จำกัด",
  "เลขทะเบียน": "0105556086736",
  "สถานะ": "ยังดำเนินกิจการอยู่",
  "วันที่จดทะเบียน": "30 พ.ค. 2556",
  "ทุนจดทะเบียน": "6,000,000.00 บาท",
  "กลุ่มธุรกิจ": "บริการ",
  "ขนาดธุรกิจ": "S",
  "ที่ตั้งสำนักงานใหญ่": "506/166  ซอยรามคำแหง 39 (เทพลีลา1) แขวงวังทองหลาง เขตวังทองหลาง กรุงเทพมหานคร",
  "กรรมการ": "นางสาวลีน่า  กัง, นางสาวนฤมล  วงค์คำ",
  "TSIC ตอนจดทะเบียน": "79120 ธุรกิจจัดนำเที่ยว",
  "วัตถุประสงค์ตอนจดทะเบียน": "ประกอบธุรกิจนำเที่ยว",
  "TSIC ล่าสุด": "86201 กิจกรรมคลินิกโรคทั่วไป",
  "วัตถุประสงค์ล่าสุด": "ประกอบกิจการบริการและดำเนินการจัดหาสถานที่และอำนวยความสะดวกในด้านต่างๆเพื่อตรวจรักษาโรค",
  "fetched_at_utc": "2025-08-12T18:05:15Z"
}