{
  "tax_id": "0105548147349",
  "ชื่อ": "บริษัท บางกอกสตาร์ คลินิก จำกัด",
  "เลขทะเบียน": "0105548147349",
  "สถานะ": "ยังดำเนินกิจการอยู่",
  "วันที่จดทะเบียน": "09 พ.ย. 2548",
  "ทุนจดทะเบียน": "2,000,000.00 บาท",
  "กลุ่มธุรกิจ": "บริการ",
  "ขนาดธุรกิจ": "M",
  "ที่ตั้งสำนักงานใหญ่": "288/30  หมู่บ้าน เนอวานา แอทเวิร์ค ลาดพร้าว - เกษตรนวมินทร์ ถนนประเสริฐมนูกิจ แขวงนวมินทร์ เขตบึงกุ่ม กรุงเทพมหานคร",
  "กรรมการ": "นายดิษฐพงศ์  สัตตบงกช, นางวิจิตรา  สัตตบงกช",
  "TSIC ตอนจดทะเบียน": "86101 กิจกรรมโรงพยาบาล",
  "วัตถุประสงค์ตอนจดทะเบียน": "ประกอบกิจการโรงพยาบาลเอกชน สถานพยาบาล รับรักษาคนไข้และผู้ป่วยเจ็บ รับทำการฝึกสอน",
  "TSIC ล่าสุด": "86201 กิจกรรมคลินิกโรคทั่วไป",
  "วัตถุประสงค์ล่าสุด": "ประกอบกิจการสถานพยาบาล รักษาโรคทั่วไป",
  "fetched_at_utc": "2025-08-13T05:45:25Z"
}