{
  "tax_id": "0105547115991",
  "ชื่อ": "บริษัท เมอริเดียน ทราเวิล จำกัด",
  "เลขทะเบียน": "0105547115991",
  "สถานะ": "ยังดำเนินกิจการอยู่",
  "วันที่จดทะเบียน": "26 ส.ค. 2547",
  "ทุนจดทะเบียน": "1,000,000.00 บาท",
  "กลุ่มธุรกิจ": "บริการ",
  "ขนาดธุรกิจ": "S",
  "ที่ตั้งสำนักงานใหญ่": "49/23 ซอย 6 ถนนสวนดอก ต.สุเทพ อ.เมืองเชียงใหม่ จ.เชียงใหม่",
  "กรรมการ": "นายพงศธร  จันทรัคคะ",
  "TSIC ตอนจดทะเบียน": "79110 ตัวแทนธุรกิจการเดินทาง",
  "วัตถุประสงค์ตอนจดทะเบียน": "ประกอบกิจการให้การบริการด้านการท่องเที่ยวทั้งในและต่างประเทศ",
  "TSIC ล่าสุด": "79110 ตัวแทนธุรกิจการเดินทาง",
  "วัตถุประสงค์ล่าสุด": "ประกอบกิจการตัวแทนจำหน่ายตั๋วเครื่องบิน",
  "fetched_at_utc": "2025-08-13T07:22:53Z"
}