{
  "tax_id": "0105554031713",
  "ชื่อ": "บริษัท อิตาเลี่ยน ไฟน์ ฟู้ดส์ จำกัด",
  "เลขทะเบียน": "0105554031713",
  "สถานะ": "ยังดำเนินกิจการอยู่",
  "วันที่จดทะเบียน": "04 มี.ค. 2554",
  "ทุนจดทะเบียน": "4,100,000.00 บาท",
  "กลุ่มธุรกิจ": "ขายปลีก",
  "ขนาดธุรกิจ": "S",
  "ที่ตั้งสำนักงานใหญ่": "9 ซอยพัฒนเวศม์ 4  แขวงพระโขนงเหนือ เขตวัฒนา กรุงเทพมหานคร",
  "กรรมการ": "นางสาวไพลิน  ศุภสกุลอนันต์",
  "TSIC ตอนจดทะเบียน": "56101 การบริการด้านอาหารในภัตตาคาร/ร้านอาหาร",
  "วัตถุประสงค์ตอนจดทะเบียน": "ประกอบกิจการร้านอาหาร รวมทั้งนำเข้า และส่งออก อาหารสด อาหารแห้ง อาหารสำเร็จรูป ทุกชนิด",
  "TSIC ล่าสุด": "47190 การขายปลีกสินค้าอื่นๆในร้านค้าทั่วไป",
  "วัตถุประสงค์ล่าสุด": "จำหน่ายสินค้าอุปโภค/บริโภค นำเข้าจากต่างประเทศ",
  "fetched_at_utc": "2025-08-12T20:55:50Z"
}