{
  "tax_id": "0105520000751",
  "ชื่อ": "บริษัท ออโต้เทคนิค (ประเทศไทย) จำกัด",
  "เลขทะเบียน": "0105520000751",
  "สถานะ": "ยังดำเนินกิจการอยู่",
  "วันที่จดทะเบียน": "19 ม.ค. 2520",
  "ทุนจดทะเบียน": "25,000,000.00 บาท",
  "กลุ่มธุรกิจ": "ขายส่ง",
  "ขนาดธุรกิจ": "L",
  "ที่ตั้งสำนักงานใหญ่": "1494  ถนนเพชรบุรีตัดใหม่ แขวงมักกะสัน เขตราชเทวี กรุงเทพมหานคร",
  "กรรมการ": "นายทาคาชิ  ฮาตะ, นายเคนทาโร่  ยามาโมโตะ, นายนาโอยะ  เซะงูจิ, นายทาเคชิ  ยาสุอิ, นางชนิดา  พงษ์เลื่องธรรม, นางอรวรรณ  วัฒนไตรภพ",
  "TSIC ตอนจดทะเบียน": "45201 การบำรุงรักษาและการซ่อมระบบเครื่องยนต์และชิ้นส่วนยานยนต์",
  "วัตถุประสงค์ตอนจดทะเบียน": "รับแก้ไข ซ่อมแซม ดัดแปลง หรือเปลี่ยนแปลงสภาพ และการบำรุงรักษาตลอดทั้งรับปฏิบัติการทางเทคนิคและบริการอย่างอื่นสำหรับยานพาหนะทุกชนิดและเครื่องจักรทุกชนิด",
  "TSIC ล่าสุด": "45101 การขายยานยนต์ใหม่ชนิดรถยนต์นั่งส่วนบุคคลรถกระบะรถตู้ และรถขนาดเล็กที่คล้ายกัน",
  "วัตถุประสงค์ล่าสุด": "การขายปลีกรถยนต์การบำรุงรักษาและการซ่อมยานยนต์",
  "fetched_at_utc": "2025-08-14T15:04:24Z"
}