{
  "tax_id": "0105559085731",
  "ชื่อ": "บริษัท อินโทร เวอร์ติคัล จำกัด",
  "เลขทะเบียน": "0105559085731",
  "สถานะ": "ยังดำเนินกิจการอยู่",
  "วันที่จดทะเบียน": "06 มิ.ย. 2559",
  "ทุนจดทะเบียน": "5,000,000.00 บาท",
  "กลุ่มธุรกิจ": "บริการ",
  "ขนาดธุรกิจ": "S",
  "ที่ตั้งสำนักงานใหญ่": "11/1  ซอยหมู่บ้านสวนแหลมทอง 2 ซอย 8 ถนนพัฒนาการ แขวงสวนหลวง เขตสวนหลวง กรุงเทพมหานคร",
  "กรรมการ": "นางสิยา  พิชิตสิงห์",
  "TSIC ตอนจดทะเบียน": "47611 ร้านขายปลีกหนังสือหนังสือพิมพ์วารสารและนิตยสาร",
  "วัตถุประสงค์ตอนจดทะเบียน": "ประกอบธุรกิจจำหน่ายปลีก-ส่ง หนังสือ หนังสือพิมพ์ วารสาร นิตยสาร และสื่อสิ่งพิมพ์อื่นๆ ทุกชนิด",
  "TSIC ล่าสุด": "56101 การบริการด้านอาหารในภัตตาคาร/ร้านอาหาร",
  "วัตถุประสงค์ล่าสุด": "จำหน่ายอาหารและเครื่องดื่ม",
  "fetched_at_utc": "2025-08-12T12:33:12Z"
}