{
  "tax_id": "0243537000144",
  "ชื่อ": "ห้างหุ้นส่วนจำกัด อีสเทอร์น ออโต",
  "เลขทะเบียน": "0243537000144",
  "สถานะ": "ยังดำเนินกิจการอยู่",
  "วันที่จดทะเบียน": "28 ก.พ. 2537",
  "ทุนจดทะเบียน": "5,000,000.00 บาท",
  "กลุ่มธุรกิจ": "ขายส่ง",
  "ขนาดธุรกิจ": "S",
  "ที่ตั้งสำนักงานใหญ่": "87/14 ถนนศุขประยูร ต.หน้าเมือง อ.เมืองฉะเชิงเทรา จ.ฉะเชิงเทรา",
  "กรรมการ": "-",
  "TSIC ตอนจดทะเบียน": "45203 การบำรุงรักษายานยนต์ทั่วไป",
  "วัตถุประสงค์ตอนจดทะเบียน": "บริการพ่นกันสนิมรถยนต์,เคลือบเงาสีรถยนต์",
  "TSIC ล่าสุด": "45203 การบำรุงรักษายานยนต์ทั่วไป",
  "วัตถุประสงค์ล่าสุด": "การให้บริการพ่นกันสนิม และเคลือบเงาสีรถยนต์",
  "fetched_at_utc": "2025-08-15T22:52:58Z"
}